setup.cfg
setup.py
ekkr_1/ekkr_1.py
ekkr_1.egg-info/PKG-INFO
ekkr_1.egg-info/SOURCES.txt
ekkr_1.egg-info/dependency_links.txt
ekkr_1.egg-info/not-zip-safe
ekkr_1.egg-info/top_level.txt