Metadata-Version: 2.1
Name: ekkr-1
Version: 0.0
Summary: ekkr_1
Author-email: ilapronin0700@gmail.com
